odoo/addons/base_conditional_image/README.rst
odoo/addons/base_conditional_image/__init__.py
odoo/addons/base_conditional_image/__manifest__.py
odoo/addons/base_conditional_image/i18n/base_conditional_image.pot
odoo/addons/base_conditional_image/i18n/custom_image.pot
odoo/addons/base_conditional_image/models/__init__.py
odoo/addons/base_conditional_image/models/abstract_image.py
odoo/addons/base_conditional_image/models/image.py
odoo/addons/base_conditional_image/readme/CONTRIBUTORS.rst
odoo/addons/base_conditional_image/readme/DESCRIPTION.rst
odoo/addons/base_conditional_image/readme/INSTALL.rst
odoo/addons/base_conditional_image/readme/USAGE.rst
odoo/addons/base_conditional_image/security/ir.model.access.csv
odoo/addons/base_conditional_image/static/description/icon.png
odoo/addons/base_conditional_image/static/description/index.html
odoo/addons/base_conditional_image/views/image_view.xml
odoo12_addon_base_conditional_image-12.0.1.0.2.dist-info/METADATA
odoo12_addon_base_conditional_image-12.0.1.0.2.dist-info/WHEEL
odoo12_addon_base_conditional_image-12.0.1.0.2.dist-info/top_level.txt
odoo12_addon_base_conditional_image-12.0.1.0.2.dist-info/RECORD
